tornado_helper/Combined.py
tornado_helper/GOES.py
tornado_helper/Helper.py
tornado_helper/TorNet.py
tornado_helper/__init__.py
tornado_helper-2.3.0.dist-info/METADATA
tornado_helper-2.3.0.dist-info/WHEEL
tornado_helper-2.3.0.dist-info/top_level.txt
tornado_helper-2.3.0.dist-info/RECORD
