Metadata-Version: 2.4
Name: tornado_helper
Version: 2.3.0
Summary: A helper package for uploading and downloading Tornado training data
Home-page: https://github.com/meyersa/tornado_helper
Author: August Meyers
Requires-Dist: requests
Requires-Dist: b2sdk
Requires-Dist: python-dotenv
Requires-Dist: aria2p
Requires-Dist: tqdm
Requires-Dist: boto3
Requires-Dist: pandas
Requires-Dist: pyproj
Requires-Dist: netcdf4
Requires-Dist: xarray
Requires-Dist: h5py
Requires-Dist: folium
Requires-Dist: ipywidgets
Dynamic: author
Dynamic: home-page
Dynamic: requires-dist
Dynamic: summary
